radiusutils/__init__.py
radiusutils/radius.py
radiusutils-0.0.2.dist-info/LICENSE
radiusutils-0.0.2.dist-info/METADATA
radiusutils-0.0.2.dist-info/WHEEL
radiusutils-0.0.2.dist-info/top_level.txt
radiusutils-0.0.2.dist-info/RECORD
